{
  "name": "Leatherling",
  "icon": "xoverhaul:leatherling_spawn_egg",
  "category": "xoverhaul:new_content/entities",
  "pages": [
    {
      "type": "patchouli:text",
      "text": "$(l)Leatherling$() is a hostile entity that appears on all surface biomes of the $(c)Overworld$() at all times. $(br2)♦ Stats ♦ $(br)❤ 5 $(br)⚔ 1️ $(br2)♦ Drops ♦ $(br)1-2 $(l:new_content/items/normal_items/leather_armor_piece)Leather Armor Piece$() (100%) $(br)1 Leather (10%)"
    },
    {
      "type": "patchouli:entity",
      "entity": "xoverhaul:leatherling"
    }
  ]
}